golem_streaming_abi/__init__.py
golem_streaming_abi-0.1.1.dist-info/METADATA
golem_streaming_abi-0.1.1.dist-info/WHEEL
golem_streaming_abi-0.1.1.dist-info/RECORD
